{"name":"Daihatsu Delta Wagon 1998","manufacturer":"Daihatsu","model":"Delta Wagon","modification":"SE high roof","produced_from":"1998 january","year":"1998","month":"January","body_type":"MV&1Box","drive":"FR","transmission":"5 speed manual","displacement_cc":"2184","frame":"KD-CR40N-HRMEX","price_of_new_car_thousands_yen_tokyo_area":"2065 (~$17200)","exterior_dimensions_lxwxh_mm":"4435 x 1695 x 1935","interior_dimensions_lxwxh_mm":"2605 x 1555 x 1340","wheel_base_mm":"2715","treads_f_r_mm":"1460 / 1445","ground_clearance_mm":"165","curb_vehicle_weight_kg":"1460","gross_vehicle_weight_kg":"","seating_capacity_persons":"8","doors_number":"4","min_turning_radius_m":"5.4","fuel_tank_capacity_l":"55","engine_model":"3C-T","max_power_net_kw_ps_rpm":"91 ps (66.93 kw) / 4000 rpm","max_torque_net_n_m_kg_m_rpm":"19.8 kg*m (194.17 N*m) / 2200 rpm","power_density":"16.04","engine_type":"Water cooling serial 4 cylinder OHC turbo","engine_information":"Excess flow room type 4 cycle vertical position","fuel_system":"Distribution type jet pump","turbocharger":"Turbo","fuel_type":"Diesel","lev_system_low_emission_vehicle":"No","compression_ratio":"22.6","bore_mm":"86","stroke_mm":"94","final_gear_ratio":"","fuel_consumption_at_10_15_modes_l_100km":"","fuel_consumption_at_60_km_h_l_100km":"","power_steering":"Yes","tires_size_front":"195/65r14 89s","tires_size_rear":"195/65r14 89s","braking_system_front":"Ventilated disk","braking_system_rear":"Drum (leading/trailing)","suspension_system_front":"Double wishbone type torsion bar spring","suspension_system_rear":"Lateral rod attaching 4 link type coil spring","sunroof_moonroof":"optional","front_fog_lamp":"yes","rear_fog_lamp":"no","xenon_headlight_discharge_lamp":"no","projector_headlight":"no","rear_wiper":"yes","front_spoiler":"optional","rear_or_roof_spoiler":"yes","abs_antilock_brake_system":"yes","tcs_traction_control_system":"no","lsd_limited_slip_differential":"no","privacy_glass":"no","uv_cutting_glass":"yes","aluminium_wheel":"optional","air_conditioner":"Dual air conditioner","wood_panel":"yes","cruise_control":"no","centralized_door_lock":"yes","power_window":"yes","steering_wheel_telescopic":"no","steering_wheel_tilt":"yes","leather_steering_wheel":"no","power_front_seat":"no","power_rear_seat":"no","leather_seat":"no","falling_down_type_rear_seat":"no","child_seat_fixed_with_seat_belt":"yes","rear_elr3_point_seat_belt":"no","front_seat_pretensioner_seat_belt":"yes","fourth_limited_front_seat_belt":"yes","side_impact_bar":"yes","airbag_driver":"yes","airbag_passenger":"yes","airbag_side":"no","audio_deck":"no","cd_player":"no","car_navigation_system":"optional","slug":"daihatsu_delta_wagon_1998_january_se_high_roof_kd_cr40n_hrmex","auto_vl_ru_id":10218}